gyazo/__about__.py
gyazo/__init__.py
gyazo/api.py
gyazo/error.py
gyazo/image.py
gyazo/py.typed
python_gyazo-2.3.0.dist-info/LICENSE
python_gyazo-2.3.0.dist-info/METADATA
python_gyazo-2.3.0.dist-info/WHEEL
python_gyazo-2.3.0.dist-info/top_level.txt
python_gyazo-2.3.0.dist-info/RECORD
