Metadata-Version: 2.1
Name: python-gyazo
Version: 2.3.0
Summary: A Python wrapper for Gyazo API
Home-page: https://github.com/ymyzk/python-gyazo
Author: Yusuke Miyazaki
Author-email: miyazaki.dev@gmail.com
License: MIT
Keywords: gyazo
Classifier: Development Status :: 5 - Production/Stable
Classifier: Intended Audience :: Developers
Classifier: License :: OSI Approved :: MIT License
Classifier: Operating System :: OS Independent
Classifier: Programming Language :: Python
Classifier: Programming Language :: Python :: 3
Classifier: Programming Language :: Python :: 3.5
Classifier: Programming Language :: Python :: 3.6
Classifier: Programming Language :: Python :: 3.7
Classifier: Programming Language :: Python :: 3.8
Classifier: Programming Language :: Python :: 3.9
Classifier: Programming Language :: Python :: 3.10
Classifier: Programming Language :: Python :: 3.11
Classifier: Programming Language :: Python :: 3 :: Only
Classifier: Topic :: Internet
Classifier: Typing :: Typed
Requires-Python: <4,>=3.5
License-File: LICENSE
Requires-Dist: python-dateutil (>=2.4)
Requires-Dist: requests (>=2.7)
Provides-Extra: docs
Requires-Dist: Jinja2 (<3) ; extra == 'docs'
Requires-Dist: MarkupSafe (<2) ; extra == 'docs'
Requires-Dist: Sphinx (<3,>=2.3) ; extra == 'docs'
Requires-Dist: sphinx-rtd-theme (<1,>=0.4) ; extra == 'docs'
Provides-Extra: mypy
Requires-Dist: mypy ; extra == 'mypy'
Requires-Dist: types-python-dateutil ; extra == 'mypy'
Requires-Dist: types-requests ; extra == 'mypy'
Provides-Extra: test
Requires-Dist: coverage (<6,>=5) ; extra == 'test'
Requires-Dist: coveralls (<2.0,>=1.1) ; extra == 'test'
Requires-Dist: flake8 (<4,>=3.3) ; extra == 'test'
Requires-Dist: pytest (<7,>=6) ; extra == 'test'
Requires-Dist: pytest-cov (<3,>=2) ; extra == 'test'
Requires-Dist: pytest-mock (<4,>=3) ; extra == 'test'
